ceed/__init__.py
ceed/ceed_style.kv
ceed/main.py
ceed/run_app.py
ceed/utils.py
ceed/analysis/__init__.py
ceed/analysis/merge_data.py
ceed/data/CeedApp_config.ini
ceed/data/CeedApp_config.yaml
ceed/function/__init__.py
ceed/function/func_widgets.py
ceed/function/param_noise.py
ceed/function/plugin/__init__.py
ceed/graphics/__init__.py
ceed/player/__init__.py
ceed/shape/__init__.py
ceed/shape/shape_widgets.py
ceed/stage/__init__.py
ceed/stage/stage_widgets.py
ceed/stage/plugin/__init__.py
ceed/storage/__init__.py
ceed/storage/controller.py
ceed/storage/storage_widgets.py
ceed/tests/__init__.py
ceed/tests/ceed_app.py
ceed/tests/common.py
ceed/tests/conftest.py
ceed/tests/test_experiment.py
ceed/tests/test_functions.py
ceed/tests/test_shapes.py
ceed/tests/test_stages.py
ceed/tests/test_app/__init__.py
ceed/tests/test_app/test_app_config.py
ceed/tests/test_app/test_basic.py
ceed/tests/test_app/test_experiment.py
ceed/tests/test_app/test_func.py
ceed/tests/test_app/test_shape.py
ceed/tests/test_app/test_stage.py
ceed/tests/test_app/examples/__init__.py
ceed/tests/test_app/examples/experiment.py
ceed/tests/test_app/examples/funcs.py
ceed/tests/test_app/examples/shapes.py
ceed/tests/test_app/examples/stages.py
ceed/view/__init__.py
ceed/view/controller.py
ceed/view/main.py
ceed/view/view_widgets.py
ceed-1.0.0.dev2.dist-info/LICENSE
ceed-1.0.0.dev2.dist-info/METADATA
ceed-1.0.0.dev2.dist-info/WHEEL
ceed-1.0.0.dev2.dist-info/entry_points.txt
ceed-1.0.0.dev2.dist-info/top_level.txt
ceed-1.0.0.dev2.dist-info/RECORD
