Metadata-Version: 2.1
Name: ceed
Version: 1.0.0.dev2
Summary: Slice stimulation and recordings.
Home-page: https://matham.github.io/ceed/
Author: Matthew Einhorn
Author-email: moiein2000@gmail.com
License: MIT
Platform: UNKNOWN
Classifier: License :: OSI Approved :: MIT License
Classifier: Topic :: Scientific/Engineering
Classifier: Topic :: System :: Hardware
Classifier: Programming Language :: Python :: 3.7
Classifier: Programming Language :: Python :: 3.8
Classifier: Operating System :: Microsoft :: Windows
Classifier: Intended Audience :: Developers
Requires-Dist: ffpyplayer
Requires-Dist: base-kivy-app (~=0.1.1)
Requires-Dist: kivy (~=2.0.0)
Requires-Dist: numpy
Requires-Dist: scikit-image
Requires-Dist: psutil
Requires-Dist: nixio (==1.4.9)
Requires-Dist: tqdm
Requires-Dist: scipy
Requires-Dist: kivy-garden.graph (~=0.4.0)
Requires-Dist: kivy-garden.collider (~=0.1.0)
Requires-Dist: McsPyDataTools
Requires-Dist: kivy-garden.drag-n-drop (~=0.1.0)
Requires-Dist: kivy-garden.painter (~=0.2.0)
Requires-Dist: trio
Requires-Dist: cpl-media (~=0.1.2)
Requires-Dist: tree-config (~=0.1.1)
Requires-Dist: pyusb
Provides-Extra: dev
Requires-Dist: pytest (>=3.6) ; extra == 'dev'
Requires-Dist: pytest-cov ; extra == 'dev'
Requires-Dist: flake8 ; extra == 'dev'
Requires-Dist: sphinx-rtd-theme ; extra == 'dev'
Requires-Dist: coveralls ; extra == 'dev'
Requires-Dist: trio ; extra == 'dev'
Requires-Dist: pytest-trio ; extra == 'dev'
Requires-Dist: pyinstaller ; extra == 'dev'
Requires-Dist: pytest-kivy (~=0.1.0.dev1) ; extra == 'dev'
Requires-Dist: pytest-dependency ; extra == 'dev'
